README.rst
setup.py
android_gendimen.egg-info/PKG-INFO
android_gendimen.egg-info/SOURCES.txt
android_gendimen.egg-info/dependency_links.txt
android_gendimen.egg-info/entry_points.txt
android_gendimen.egg-info/not-zip-safe
android_gendimen.egg-info/requires.txt
android_gendimen.egg-info/top_level.txt
gendimen/__init__.py