Metadata-Version: 1.1
Name: android-gendimen
Version: 0.1
Summary: A simple tool for android dimens.xml
Home-page: http://github.com/rishubil/android_gendimen
Author: Nesswit
Author-email: rishubil@gmail.com
License: Apache License 2.0
Keywords: android generator xml dimen dimension
Platform: UNKNOWN
Classifier: Development Status :: 4 - Beta
Classifier: License :: OSI Approved :: Apache Software License
Classifier: Programming Language :: Python :: 2.7
Classifier: Topic :: Software Development :: Code Generators
